notion/__init__.py
notion/client.py
notion/converter.py
notion/logger.py
notion/maps.py
notion/markdown.py
notion/monitor.py
notion/operations.py
notion/record.py
notion/renderer.py
notion/settings.py
notion/space.py
notion/store.py
notion/user.py
notion/utils.py
notion/block/__init__.py
notion/block/basic.py
notion/block/children.py
notion/block/database.py
notion/block/embed.py
notion/block/inline.py
notion/block/media.py
notion/block/types.py
notion/block/upload.py
notion/block/collection/__init__.py
notion/block/collection/basic.py
notion/block/collection/children.py
notion/block/collection/common.py
notion/block/collection/media.py
notion/block/collection/query.py
notion/block/collection/view.py
notion_py-0.0.10.dist-info/LICENSE
notion_py-0.0.10.dist-info/METADATA
notion_py-0.0.10.dist-info/WHEEL
notion_py-0.0.10.dist-info/top_level.txt
notion_py-0.0.10.dist-info/RECORD
