Metadata-Version: 2.1
Name: notion-py
Version: 0.0.10
Summary: (Fork of) Unofficial Python API client for Notion.so
Home-page: https://github.com/arturtamborski/notion-py
Author: Artur Tamborski
Author-email: tamborskiartur@gmail.com
Maintainer: Artur Tamborski
Maintainer-email: tamborskiartur@gmail.com
License: UNKNOWN
Keywords: python3,notion,api-client
Platform: UNKNOWN
Classifier: License :: OSI Approved :: MIT License
Classifier: Programming Language :: Python :: 3
Classifier: Operating System :: OS Independent
Requires-Python: >=3.6
